{
    "LOCALE_ENGLISH": "Inglês",
    "LOCALE_ENGLISH_SAFE": "Inglês (Censurado)",
    "LOCALE_FRENCH": "Français",
    "LOCALE_GERMAN": "Alemão",
    "LOCALE_ITALIAN": "Italiano",
    "LOCALE_JAPANESE_PARTIAL": "Japonês (Parcial)",
    "LOCALE_KOREAN": "Coreano",
    "LOCALE_POLISH": "Polonês",
    "LOCALE_PORTUGUESE": "Português",
    "LOCALE_RUSSIAN": "Russo",
    "LOCALE_SIMPLIFIED_CHINESE": "Chinês simplificado",
    "LOCALE_SPANISH": "Español",
    "LOCALE_TRADITIONAL_CHINESE": "Chinês tradicional"
}