{
    "LOCALE_ENGLISH": "Inglés",
    "LOCALE_ENGLISH_SAFE": "Inglés (censura)",
    "LOCALE_FRENCH": "Français",
    "LOCALE_GERMAN": "Alemán",
    "LOCALE_ITALIAN": "Italiano",
    "LOCALE_JAPANESE_PARTIAL": "Japonés (parcial)",
    "LOCALE_KOREAN": "Coreano",
    "LOCALE_POLISH": "Polaco",
    "LOCALE_PORTUGUESE": "Portugués",
    "LOCALE_RUSSIAN": "Ruso",
    "LOCALE_SIMPLIFIED_CHINESE": "Chino simplificado",
    "LOCALE_SPANISH": "Español",
    "LOCALE_TRADITIONAL_CHINESE": "Chino tradicional"
}